umls_api_client/UMLS.py
umls_api_client/__init__.py
umls_api_client-0.0.6.dist-info/METADATA
umls_api_client-0.0.6.dist-info/WHEEL
umls_api_client-0.0.6.dist-info/licenses/LICENSE
umls_api_client-0.0.6.dist-info/RECORD
