Metadata-Version: 2.1
Name: umls_api_client
Version: 0.0.6
Summary: Class to interact with the UMLS REST API
Project-URL: Homepage, https://github.com/Naveen-V-J/umls-api
Project-URL: Bug Tracker, https://github.com/Naveen-V-J/umls-api/issues
Author-email: Naveen Jayakody <naveenjayakody12@gmail.com>
License-File: LICENSE
Classifier: License :: OSI Approved :: MIT License
Classifier: Operating System :: OS Independent
Classifier: Programming Language :: Python :: 3
Requires-Python: >=3.10
Requires-Dist: ratelimit
Requires-Dist: requests
